plone.i18n-5.1.1-py3.13-nspkg.pth
plone/i18n/__init__.py
plone/i18n/configure.zcml
plone/i18n/interfaces.py
plone/i18n/overrides.zcml
plone/i18n/utility.py
plone/i18n/locales/README.txt
plone/i18n/locales/__init__.py
plone/i18n/locales/cctld.py
plone/i18n/locales/configure.zcml
plone/i18n/locales/countries.py
plone/i18n/locales/interfaces.py
plone/i18n/locales/languages.py
plone/i18n/locales/browser/__init__.py
plone/i18n/locales/browser/configure.zcml
plone/i18n/locales/browser/country-flags/ad.gif
plone/i18n/locales/browser/country-flags/ae.gif
plone/i18n/locales/browser/country-flags/af.gif
plone/i18n/locales/browser/country-flags/ag.gif
plone/i18n/locales/browser/country-flags/ai.gif
plone/i18n/locales/browser/country-flags/al.gif
plone/i18n/locales/browser/country-flags/am.gif
plone/i18n/locales/browser/country-flags/an.gif
plone/i18n/locales/browser/country-flags/ao.gif
plone/i18n/locales/browser/country-flags/aq.gif
plone/i18n/locales/browser/country-flags/ar.gif
plone/i18n/locales/browser/country-flags/as.gif
plone/i18n/locales/browser/country-flags/at.gif
plone/i18n/locales/browser/country-flags/au.gif
plone/i18n/locales/browser/country-flags/aw.gif
plone/i18n/locales/browser/country-flags/az.gif
plone/i18n/locales/browser/country-flags/ba.gif
plone/i18n/locales/browser/country-flags/bb.gif
plone/i18n/locales/browser/country-flags/bd.gif
plone/i18n/locales/browser/country-flags/be.gif
plone/i18n/locales/browser/country-flags/bf.gif
plone/i18n/locales/browser/country-flags/bg.gif
plone/i18n/locales/browser/country-flags/bh.gif
plone/i18n/locales/browser/country-flags/bi.gif
plone/i18n/locales/browser/country-flags/bj.gif
plone/i18n/locales/browser/country-flags/bl.gif
plone/i18n/locales/browser/country-flags/bm.gif
plone/i18n/locales/browser/country-flags/bn.gif
plone/i18n/locales/browser/country-flags/bo.gif
plone/i18n/locales/browser/country-flags/bq.gif
plone/i18n/locales/browser/country-flags/br.gif
plone/i18n/locales/browser/country-flags/bs.gif
plone_i18n-5.1.1.dist-info/METADATA
plone_i18n-5.1.1.dist-info/WHEEL
plone_i18n-5.1.1.dist-info/namespace_packages.txt
plone_i18n-5.1.1.dist-info/top_level.txt
plone_i18n-5.1.1.dist-info/RECORD
