Metadata-Version: 2.4
Name: plone.i18n
Version: 5.1.1
Summary: Advanced i18n/l10n features
Home-page: https://github.com/plone/plone.i18n
Author: Plone Foundation
Author-email: releaseteam@plone.org
License: GPL version 2
Keywords: i18n l10n Plone
Classifier: Development Status :: 5 - Production/Stable
Classifier: Environment :: Web Environment
Classifier: Framework :: Plone
Classifier: Framework :: Plone :: 6.0
Classifier: Framework :: Plone :: 6.1
Classifier: Framework :: Plone :: Core
Classifier: Framework :: Zope :: 5
Classifier: License :: OSI Approved :: GNU General Public License v2 (GPLv2)
Classifier: Operating System :: OS Independent
Classifier: Programming Language :: Python
Classifier: Programming Language :: Python :: 3.8
Classifier: Programming Language :: Python :: 3.9
Classifier: Programming Language :: Python :: 3.10
Classifier: Programming Language :: Python :: 3.11
Requires-Python: >=3.8
Requires-Dist: setuptools
Requires-Dist: plone.autoform
Requires-Dist: plone.registry
Requires-Dist: plone.subrequest
Requires-Dist: plone.supermodel
Requires-Dist: Products.CMFCore
Requires-Dist: Unidecode>=1.0.22
Requires-Dist: Zope
Requires-Dist: zope.globalrequest
Provides-Extra: test
Requires-Dist: plone.app.contenttypes[test]; extra == "test"
Requires-Dist: plone.app.multilingual; extra == "test"
Requires-Dist: plone.app.testing; extra == "test"
Requires-Dist: plone.base; extra == "test"
Requires-Dist: zope.browserresource; extra == "test"
Dynamic: author
Dynamic: author-email
Dynamic: classifier
Dynamic: description
Dynamic: description-content-type
Dynamic: home-page
Dynamic: keywords
Dynamic: license
Dynamic: provides-extra
Dynamic: requires-dist
Dynamic: requires-python
Dynamic: summary
